Metadata-Version: 2.1
Name: plateFinder
Version: 1.0.0
Summary: A package find the plate
Author: Guido Xhindoli
Author-email: <mail@gmail.com>
Keywords: plateFinder,pythonsdaal,plate,sda,SDA
Classifier: Development Status :: 1 - Planning
Classifier: Intended Audience :: Developers
Classifier: Programming Language :: Python :: 3
Classifier: Operating System :: Unix
Classifier: Operating System :: MacOS :: MacOS X
Classifier: Operating System :: Microsoft :: Windows
Requires-Dist: openpyxl
Requires-Dist: pandas
Requires-Dist: pyarrow
